ioc_writer/__init__.py
ioc_writer/ioc_api.py
ioc_writer/ioc_common.py
ioc_writer/ioc_et.py
ioc_writer/managers/__init__.py
ioc_writer/managers/downgrade_11.py
ioc_writer/managers/upgrade_10.py
ioc_writer/utils/__init__.py
ioc_writer/utils/xmlutils.py
ioc_writer-0.3.2.dist-info/DESCRIPTION.rst
ioc_writer-0.3.2.dist-info/METADATA
ioc_writer-0.3.2.dist-info/RECORD
ioc_writer-0.3.2.dist-info/WHEEL
ioc_writer-0.3.2.dist-info/metadata.json
ioc_writer-0.3.2.dist-info/top_level.txt
