Metadata-Version: 2.0
Name: ioc-writer
Version: 0.3.2
Summary: API providing a limited CRUD for manipulating OpenIOC formatted Indicators of Compromise.
Home-page: http://www.github.com/mandiant/ioc_writer/
Author: William Gibb
Author-email: william.gibb@mandiant.com
License: UNKNOWN
Platform: UNKNOWN
Classifier: Development Status :: 4 - Beta
Classifier: Environment :: Console
Classifier: Intended Audience :: Developers
Classifier: Intended Audience :: Information Technology
Classifier: Intended Audience :: System Administrators
Classifier: License :: OSI Approved :: Apache Software License
Classifier: Natural Language :: English
Classifier: Operating System :: OS Independent
Classifier: Programming Language :: Python :: 2.7
Classifier: Programming Language :: Python :: 3.4
Classifier: Programming Language :: Python :: 3.5
Classifier: Topic :: Security
Classifier: Topic :: Text Processing :: Markup :: XML
Requires-Dist: lxml
